{
  "parent": "me:alloy/bronze_ingot",
  "criteria": {
    "steel": {
      "conditions": {
        "items": [
          {
            "items": [
              "me:steel_ingot"
            ]
          }
        ]
      },
      "trigger": "minecraft:inventory_changed"
    }
  },
  "display": {
    "announce_to_chat": true,
    "description": {
      "translate": "advancements.alloy.steel.description"
    },
    "frame": "task",
    "hidden": false,
    "icon": {
      "item": "me:steel_ingot"
    },
    "show_toast": true,
    "title": {
      "translate": "advancements.alloy.steel.title"
    }
  },
  "requirements": [
    [
      "steel"
    ]
  ]
}