{
  "parent": "minecraft:recipes/root",
  "criteria": {
    "has_citrine_shard": {
      "conditions": {
        "items": [
          {
            "items": [
              "me:citrine_shard"
            ]
          }
        ]
      },
      "trigger": "minecraft:inventory_changed"
    },
    "has_the_recipe": {
      "conditions": {
        "recipe": "me:citrine_block"
      },
      "trigger": "minecraft:recipe_unlocked"
    }
  },
  "requirements": [
    [
      "has_citrine_shard",
      "has_the_recipe"
    ]
  ],
  "rewards": {
    "recipes": [
      "me:citrine_block"
    ]
  },
  "sends_telemetry_event": false
}