{
  "parent": "minecraft:recipes/root",
  "criteria": {
    "has_the_recipe": {
      "conditions": {
        "recipe": "me:waxed_aged_thatch_wall"
      },
      "trigger": "minecraft:recipe_unlocked"
    },
    "has_waxed_aged_thatch": {
      "conditions": {
        "items": [
          {
            "items": [
              "me:waxed_aged_thatch"
            ]
          }
        ]
      },
      "trigger": "minecraft:inventory_changed"
    }
  },
  "requirements": [
    [
      "has_waxed_aged_thatch",
      "has_the_recipe"
    ]
  ],
  "rewards": {
    "recipes": [
      "me:waxed_aged_thatch_wall"
    ]
  },
  "sends_telemetry_event": false
}