{
  "variants": {
    "facing=down": {
      "model": "me:block/glowstone_cluster",
      "x": 180
    },
    "facing=east": {
      "model": "me:block/glowstone_cluster",
      "x": 90,
      "y": 90
    },
    "facing=north": {
      "model": "me:block/glowstone_cluster",
      "x": 90
    },
    "facing=south": {
      "model": "me:block/glowstone_cluster",
      "x": 90,
      "y": 180
    },
    "facing=up": {
      "model": "me:block/glowstone_cluster"
    },
    "facing=west": {
      "model": "me:block/glowstone_cluster",
      "x": 90,
      "y": 270
    }
  }
}