{
  "required": true,
  "minVersion": "0.8",
  "package": "net.sevenstars.middleearth.mixin",
  "compatibilityLevel": "JAVA_17",
  "mixins": [
    "AbstractHorseEntityMixin",
    "BannerPatternRegisterMixin",
    "BlockMixin",
    "ChunkGenerationStepMixin",
    "ChunkGeneratorMixin",
    "EntityDataSaverMixin",
    "EntitySpawnMixin",
    "FishingBobberEntityMixin",
    "FoliagePlacerTypeInvoker",
    "GrassBlockMixin",
    "LivingEntityMixin",
    "PigEntityMixin",
    "PlayerEntityMixin",
    "PotionEntityMixin",
    "PowderSnowBlockMixin",
    "RepairItemRecipeMixin",
    "ServerPlayerEntityMixin",
    "ServerPlayNetworkHandlerMixin",
    "ShearItemMixin",
    "ShovelItemMixin",
    "TrunkPlacerTypeInvoker"
  ],
  "client": [
    "IntegratedServerLoaderMixin",
    "client.AbstractClientPlayerEntityMixin",
    "client.BakedModelManagerMixin",
    "client.BipedEntityModelMixin",
    "client.BipedEntityRendererMixin",
    "client.GuiRendererMixin",
    "client.HeldItemRendererMixin",
    "client.InGameHudMixin",
    "client.LivingEntityRendererMixin",
    "client.LivingEntityRenderStateMixin",
    "client.MouseMixin"
  ],
  "server": [
  ],
  "injectors": {
    "defaultRequire": 1
  }
}
