{
  "parent": "block/block",
  "textures": {
    "top": "middle-earth:block/chiseled_dolomite_bookshelf_top",
    "side": "middle-earth:block/chiseled_dolomite_bookshelf_side",
    "front": "middle-earth:block/chiseled_dolomite_bookshelf",
    "particle": "#top"
  },
  "elements": [
    {
      "name": "chiseled_bookshelf_body",
      "from": [0, 0, 0],
      "to": [16, 16, 16],
      "faces": {
        "north": {"uv": [0, 0, 16, 16], "texture": "#front"},
        "east": {"uv": [0, 0, 16, 16], "texture": "#side"},
        "south": {"uv": [0, 0, 16, 16], "texture": "#side"},
        "west": {"uv": [0, 0, 16, 16], "texture": "#side"},
        "up": {"uv": [0, 0, 16, 16], "texture": "#top"},
        "down": {"uv": [0, 0, 16, 16], "texture": "#top"}
      }
    }
  ]
}
