{
  "carvers": {
  },
  "downfall": 0.0,
  "effects": {
    "additions_sound": {
      "sound": "minecraft:ambient.nether_wastes.additions",
      "tick_chance": 0.0111
    },
    "ambient_sound": "minecraft:ambient.nether_wastes.loop",
    "fog_color": 3344392,
    "mood_sound": {
      "block_search_extent": 8,
      "offset": 2.0,
      "sound": "minecraft:ambient.nether_wastes.mood",
      "tick_delay": 6000
    },
    "music": {
      "max_delay": 24000,
      "min_delay": 12000,
      "replace_current_music": false,
      "sound": "minecraft:music.nether.nether_wastes"
    },
    "sky_color": 2432285,
    "fog_color": 1643797,
    "water_color": 6450777,
    "water_fog_color": 1513734,
    "grass_color": 3548710,
    "foliage_color": 2168856,
	"particle": {
      "options": {
        "type": "smoke"
      },
      "probability": 0.005
    }
  },
  "features": [
    [],
    [
	  "me:mordor/lava_lake"
	],
    [],
    [],
    [],
    [],
    [
	  "me:mordor/ore_mordor_dirt",
	  "me:mordor/ore_basalt"
	],
    [],
    [
	  "me:patch/tough_berry",
	  "me:mordor/patch_mordor_lichen",
	  "me:mordor/patch_mordor_lichen_fan",
	],
    []
  ],
  "has_precipitation": false,
  "spawn_costs": {},
  "spawners": {
    "ambient": [],
	"creature": [
	],
    "axolotls": [],
    "misc": [],
    "monster": [
	],
    "underground_water_creature": [],
    "water_ambient": [],
    "water_creature": []
  },
  "temperature": 2.0
}